MANIFEST.in
README.client.rst
README.md
setup.py
zeus/__init__.py
zeus/client.py
zeus/core.py
zeus/zeus_sk.py
zeus_client.egg-info/PKG-INFO
zeus_client.egg-info/SOURCES.txt
zeus_client.egg-info/dependency_links.txt
zeus_client.egg-info/entry_points.txt
zeus_client.egg-info/requires.txt
zeus_client.egg-info/top_level.txt