Metadata-Version: 1.1
Name: zeus-client
Version: 0.1.5
Summary: Zeus client
Home-page: https://github.com/grnet/zeus
Author: GRNET Zeus developers
Author-email: dev@zeus.grnet.gr
License: UNKNOWN
Platform: UNKNOWN
Classifier: Development Status :: 3 - Alpha
Classifier: Programming Language :: Python :: 2
Classifier: Programming Language :: Python :: 2.7
